checker/__init__.py
checker/decorators.py
checker/main.py
ad_ctf_paas_lib-0.0.3.dist-info/LICENSE
ad_ctf_paas_lib-0.0.3.dist-info/METADATA
ad_ctf_paas_lib-0.0.3.dist-info/WHEEL
ad_ctf_paas_lib-0.0.3.dist-info/top_level.txt
ad_ctf_paas_lib-0.0.3.dist-info/RECORD
