Metadata-Version: 2.1
Name: ad-ctf-paas-lib
Version: 0.0.3
Summary: Library that help to write checkers
Home-page: UNKNOWN
Author: ivanh
Author-email: ivanhahanov13@gmail.com
License: UNKNOWN
Platform: UNKNOWN
License-File: LICENSE
